animate_puml/__init__.py
animate_puml/app.py
animate_puml/py.typed
animate_puml-0.6.0.dist-info/WHEEL
animate_puml-0.6.0.dist-info/METADATA
animate_puml-0.6.0.dist-info/entry_points.txt
animate_puml-0.6.0.dist-info/RECORD
