Metadata-Version: 2.1
Name: animate-puml
Version: 0.6.0
Summary: Simple animation of PlantUML diagrams
Home-page: https://namuan.github.io/animate-puml
License: MIT
Author: namuan
Author-email: github@deskriders.dev
Requires-Python: >=3.8.0,<4.0
Classifier: Development Status :: 4 - Beta
Classifier: Intended Audience :: Developers
Classifier: License :: OSI Approved :: MIT License
Classifier: Operating System :: OS Independent
Classifier: Programming Language :: Python
Classifier: Programming Language :: Python :: 3
Classifier: Programming Language :: Python :: 3.8
Classifier: Programming Language :: Python :: 3.9
Classifier: Programming Language :: Python :: 3.10
Classifier: Programming Language :: Python :: 3.11
Classifier: Programming Language :: Python :: 3
Classifier: Programming Language :: Python :: 3.10
Classifier: Programming Language :: Python :: 3.8
Classifier: Programming Language :: Python :: 3.9
Classifier: Topic :: Software Development :: Libraries :: Python Modules
Classifier: Typing :: Typed
Requires-Dist: pillow (>=9.4.0,<10.0.0)
Requires-Dist: py-executable-checklist (==1.4.0)
Requires-Dist: pygifsicle (>=1.0.7,<2.0.0)
Requires-Dist: pytest (>=7.2.0,<8.0.0)
Requires-Dist: python-dotenv (>=0.21.0,<0.22.0)
Requires-Dist: rich (>=13.0.0,<14.0.0)
Project-URL: Documentation, https://namuan.github.io/animate-puml
Project-URL: Repository, https://github.com/namuan/animate-puml
